popgen/__init__.py
popgen/config.py
popgen/data.py
popgen/draw.py
popgen/ipf.py
popgen/output.py
popgen/project.py
popgen/reweighting.py
popgen23-1.0.2.dist-info/LICENSE
popgen23-1.0.2.dist-info/METADATA
popgen23-1.0.2.dist-info/WHEEL
popgen23-1.0.2.dist-info/top_level.txt
popgen23-1.0.2.dist-info/RECORD
